mania2json/__init__.py
mania2json/core.py
mania2json-0.1.1.dist-info/licenses/LICENSE
mania2json-0.1.1.dist-info/METADATA
mania2json-0.1.1.dist-info/WHEEL
mania2json-0.1.1.dist-info/top_level.txt
mania2json-0.1.1.dist-info/RECORD
